bahc/__init__.py
bahc/bahc.py
bahc-2.0.3.dist-info/METADATA
bahc-2.0.3.dist-info/WHEEL
bahc-2.0.3.dist-info/top_level.txt
bahc-2.0.3.dist-info/RECORD
