Metadata-Version: 2.1
Name: bahc
Version: 2.0.3
Summary: Bootstrap Average Hierarchical Clustering for filtering covariance matrices
Home-page: https://github.com/bongiornoc/bahc
Author: Christian Bongiorno
Author-email: christian.bongiorno@centralesupelec.fr
Classifier: Programming Language :: Python :: 3
Classifier: License :: OSI Approved :: MIT License
Classifier: Operating System :: OS Independent
Requires-Python: >=3.10
Requires-Dist: numpy
Requires-Dist: scipy
Requires-Dist: statsmodels
